qibullet/__init__.py
qibullet/base_controller.py
qibullet/camera.py
qibullet/controller.py
qibullet/fsr.py
qibullet/helpers.py
qibullet/imu.py
qibullet/joint.py
qibullet/laser.py
qibullet/link.py
qibullet/nao_virtual.py
qibullet/pepper_virtual.py
qibullet/robot_module.py
qibullet/robot_posture.py
qibullet/robot_virtual.py
qibullet/romeo_virtual.py
qibullet/ros_wrapper.py
qibullet/sensor.py
qibullet/simulation_manager.py
qibullet/tools.py
qibullet/robot_data/LICENSE
qibullet/robot_data/__init__.py
qibullet/robot_data/meshes.zip
qibullet/robot_data/nao.urdf
qibullet/robot_data/pepper.urdf
qibullet/robot_data/romeo.urdf
qibullet/robot_data/installers/meshes_installer_27.pyc
qibullet/robot_data/installers/meshes_installer_35.pyc
qibullet/robot_data/installers/meshes_installer_36.pyc
qibullet/robot_data/installers/meshes_installer_37.pyc
qibullet/robot_data/installers/meshes_installer_38.pyc
qibullet/robot_data/installers/meshes_installer_39.pyc
qibullet-1.4.6.dist-info/LICENSE
qibullet-1.4.6.dist-info/METADATA
qibullet-1.4.6.dist-info/WHEEL
qibullet-1.4.6.dist-info/top_level.txt
qibullet-1.4.6.dist-info/RECORD
