Metadata-Version: 2.1
Name: qibullet
Version: 1.4.6
Summary: Bullet-based simulation for SoftBank Robotics' robots
Home-page: https://github.com/softbankrobotics-research/qibullet
Author: Maxime Busy, Maxime Caniot
Author-email: 
Keywords: physics simulation,robotics,naoqi,softbank,pepper,nao,romeo,robot
Classifier: License :: OSI Approved :: Apache Software License
Classifier: Programming Language :: Python :: 2.7
Classifier: Programming Language :: Python :: 3.5
Classifier: Programming Language :: Python :: 3.6
Classifier: Programming Language :: Python :: 3.7
Classifier: Programming Language :: Python :: 3.8
Classifier: Programming Language :: Python :: 3.9
Classifier: Intended Audience :: Science/Research
Classifier: Intended Audience :: Developers
Classifier: Operating System :: POSIX :: Linux
Classifier: Operating System :: MacOS
Classifier: Operating System :: Microsoft
Classifier: Topic :: Games/Entertainment :: Simulation
Classifier: Topic :: Scientific/Engineering :: Artificial Intelligence
License-File: LICENSE
Requires-Dist: numpy
Requires-Dist: pybullet
